<route id="59" town="Town12">
  <weathers>
    <weather route_percentage="0" cloudiness="40.0" precipitation="100.0" precipitation_deposits="90.0" wetness="0.0" wind_intensity="100.0" sun_azimuth_angle="-1.0" sun_altitude_angle="0.0" fog_density="7.0"/>
    <weather route_percentage="100" cloudiness="100.0" precipitation="60.0" precipitation_deposits="60.0" wetness="0.0" wind_intensity="60.0" sun_azimuth_angle="-1.0" sun_altitude_angle="45.0" fog_density="50.0"/>
  </weathers>
  <waypoints>
    <position x="-2594.6" y="855.2" z="313.2"/>
    <position x="-2863.3" y="783.3" z="316.3"/>
  </waypoints>
  <scenarios>
    <scenario name="InvadingTurn_4" type="InvadingTurn">
      <trigger_point x="-2748.6" y="833.4" z="313.7" yaw="168.9"/>
      <distance value="90"/>
      <offset value="0.2"/>
    </scenario>
  </scenarios>
</route>